llm_reasoner/__init__.py
llm_reasoner/__main__.py
llm_reasoner/commands.py
llm_reasoner/engine.py
llm_reasoner/interface.py
llm_reasoner/models.py
llm_reasoner/settings.py
llm_reasoner_upload/llm_reasoner/__init__.py
llm_reasoner_upload/llm_reasoner/__main__.py
llm_reasoner_upload/llm_reasoner/commands.py
llm_reasoner_upload/llm_reasoner/engine.py
llm_reasoner_upload/llm_reasoner/interface.py
llm_reasoner_upload/llm_reasoner/models.py
llm_reasoner_upload/llm_reasoner/settings.py
llm_reasoner_upload/tests/__init__.py
llm_reasoner_upload/tests/test_llm_reasoner.py
llm_reasoner-0.1.10.dist-info/LICENSE
llm_reasoner-0.1.10.dist-info/METADATA
llm_reasoner-0.1.10.dist-info/WHEEL
llm_reasoner-0.1.10.dist-info/entry_points.txt
llm_reasoner-0.1.10.dist-info/top_level.txt
llm_reasoner-0.1.10.dist-info/RECORD
