Metadata-Version: 2.2
Name: llm-reasoner
Version: 0.1.10
Summary: Transform any LLM into a methodical thinker that excels at systematic reasoning like OpenAI o1 and DeepSeek R1
Author-email: Harish Santhanalakshmi Ganesan <harishsg99@gmail.com>
License: MIT License
Requires-Python: >=3.8
License-File: LICENSE
Requires-Dist: litellm>=1.0.0
Requires-Dist: click>=8.0.0
Requires-Dist: rich>=12.0.0
Requires-Dist: streamlit>=1.0.0
Requires-Dist: pydantic>=2.0.0
Requires-Dist: pytest>=8.3.4
Requires-Dist: pytest-asyncio>=0.24.0
Requires-Dist: build>=1.2.2.post1
Requires-Dist: twine>=6.1.0
Provides-Extra: dev
Requires-Dist: pytest>=6.0; extra == "dev"
Requires-Dist: pytest-asyncio>=0.24.0; extra == "dev"
Requires-Dist: black>=22.0; extra == "dev"
Requires-Dist: mypy>=0.900; extra == "dev"
Requires-Dist: build>=1.0.0; extra == "dev"
Requires-Dist: twine>=4.0.0; extra == "dev"
